{
  "protechlog195": {
    "category": "record",
    "sounds": [
      {
        "name": "haywensmpcollection:protech_log_195",
        "stream": true
      }
    ]
  },
  "protech_log204": {
    "category": "record",
    "sounds": [
      {
        "name": "haywensmpcollection:protech_log_204",
        "stream": true
      }
    ]
  },
  "protech_log290": {
    "category": "record",
    "sounds": [
      {
        "name": "haywensmpcollection:protech_log_290",
        "stream": true
      }
    ]
  },
  "protech_log309": {
    "category": "record",
    "sounds": [
      {
        "name": "haywensmpcollection:protech_log_309",
        "stream": true
      }
    ]
  },
  "protech_log_newemployee": {
    "category": "record",
    "sounds": [
      {
        "name": "haywensmpcollection:protech_paras_new_employee_welcome",
        "stream": true
      }
    ]
  },
  "protech_personallog1": {
    "category": "record",
    "sounds": [
      {
        "name": "haywensmpcollection:protech_personal_log_1_d",
        "stream": true
      }
    ]
  },
  "protech_personallog2": {
    "category": "record",
    "sounds": [
      {
        "name": "haywensmpcollection:protech_personal_log_2_d",
        "stream": true
      }
    ]
  },
  "nvx_cave1": {
    "category": "record",
    "sounds": [
      {
        "name": "haywensmpcollection:nova_cave",
        "stream": true
      }
    ]
  },
  "nvxa_cave2": {
    "category": "record",
    "sounds": [
      {
        "name": "haywensmpcollection:nova_cave_2",
        "stream": true
      }
    ]
  },
  "nvxa_cave_5thfloor": {
    "category": "record",
    "sounds": [
      {
        "name": "haywensmpcollection:novas_cave_5th_floor_project_horizon_",
        "stream": true
      }
    ]
  },
  "nvxa_blackice": {
    "category": "record",
    "sounds": [
      {
        "name": "haywensmpcollection:project_black_ice",
        "stream": true
      }
    ]
  },
  "hwn_mmdr_sai": {
    "category": "record",
    "sounds": [
      {
        "name": "haywensmpcollection:metallic_material_depo_report",
        "stream": true
      }
    ]
  },
  "hwnprammd_gtmureportlog": {
    "category": "record",
    "sounds": [
      {
        "name": "haywensmpcollection:praa_mmd_gtmu_report_log",
        "stream": true
      }
    ]
  }
}